MattThePerson_CustomLibraries/__init__.py
MattThePerson_CustomLibraries/media_generator/__init__.py
MattThePerson_CustomLibraries/media_generator/media_generator.py
MattThePerson_CustomLibraries/media_generator/lib/stills.py
MattThePerson_CustomLibraries/my_utilities/__init__.py
MattThePerson_CustomLibraries/my_utilities/bookmarks_getter.py
MattThePerson_CustomLibraries/my_utilities/image_metadata.py
MattThePerson_CustomLibraries/my_utilities/json_handler.py
MattThePerson_CustomLibraries/my_utilities/string_parser.py
MattThePerson_CustomLibraries/sqlite_api/__init__.py
MattThePerson_CustomLibraries/video_analyser/__init__.py
MattThePerson_CustomLibraries/video_analyser/video_analyser.py
MattThePerson_CustomLibraries/video_preview_grid_maker/__init__.py
MattThePerson_CustomLibraries/video_preview_grid_maker/video_preview_grid_maker.py
matttheperson_customlibs-0.0.1.dist-info/METADATA
matttheperson_customlibs-0.0.1.dist-info/WHEEL
matttheperson_customlibs-0.0.1.dist-info/RECORD
